Metadata-Version: 2.3
Name: matrix-zion-aws
Version: 0.1.0
Summary: Extensão AWS para o framework Matrix - Plugin para serviços AWS
License: MIT
Keywords: microservices,aws,matrix,plugin,boto3,dynamodb
Author: Tuyoshi Vinicius
Author-email: tuyoshi.vinicius@gmail.com
Requires-Python: >=3.10
Classifier: Development Status :: 3 - Alpha
Classifier: Intended Audience :: Developers
Classifier: License :: OSI Approved :: MIT License
Classifier: Programming Language :: Python :: 3
Classifier: Programming Language :: Python :: 3.10
Classifier: Programming Language :: Python :: 3.11
Classifier: Programming Language :: Python :: 3.12
Classifier: Topic :: Software Development :: Libraries :: Python Modules
Classifier: Topic :: System :: Distributed Computing
Provides-Extra: dev
Requires-Dist: boto3 (>=1.34.0)
Requires-Dist: matrix-zion (>=0.1.0)
Requires-Dist: moto[sns,sqs] (>=5.0.0) ; extra == "dev"
Requires-Dist: pytest (>=8.0.0) ; extra == "dev"
Project-URL: Bug Reports, https://github.com/tuyoshivinicius/python-microservice-v2/issues
Project-URL: Documentation, https://github.com/tuyoshivinicius/python-microservice-v2/blob/main/README.md
Project-URL: Homepage, https://github.com/tuyoshivinicius/python-microservice-v2
Project-URL: Repository, https://github.com/tuyoshivinicius/python-microservice-v2
